setup.py
dsnd_math_probability/Binomialdistribution.py
dsnd_math_probability/Gaussiandistribution.py
dsnd_math_probability/Generaldistribution.py
dsnd_math_probability/__init__.py
dsnd_math_probability.egg-info/PKG-INFO
dsnd_math_probability.egg-info/SOURCES.txt
dsnd_math_probability.egg-info/dependency_links.txt
dsnd_math_probability.egg-info/not-zip-safe
dsnd_math_probability.egg-info/top_level.txt