Metadata-Version: 1.0
Name: dsnd-math-probability
Version: 0.1
Summary: Gaussian and Binomial Distributions
Home-page: UNKNOWN
Author: Kawalpreet Deol
Author-email: UNKNOWN
License: UNKNOWN
Platform: UNKNOWN
